Workbook

Sheet 品牌原始数据
A1: 山池咖啡采集表（近12个月数据）
A2: 月份 | B2: 基础经营数据（推算拉新好友） | G2: 会员数据 | J2: 私域数据 | L2: 项目 | M2: 数值 | N2: 说明
A3: 近12个月 | B3: 门店数 | C3: 客流量 | D3: 订单数 (小程序产生的订单数) | E3: 消费人数 (小程序产生的消费人数) | F3: 客单价（元） | G3: 会员体量 | H3: 会员消费人数 | I3: 会员消费频次（次/月） | J3: 企微现有好友总数 | L3: 人均拉新成本预算 | N3: 私域拉新的利益点成本；用于判断拉新覆盖率，利益点越高，用户更容易进品牌私域池
A4: 45839 | B4: 13 | C4: 80089 | D4: 79867 | E4: 32231 | F4: 55.71 | G4: 805194 | H4: - | I4: - | J4: 0 | K4: 0.40243979
A5: 45870 | B5: 13 | C5: 84520 | D5: 84302 | E5: 36284 | F5: 58.62 | G5: 836670 | H5: - | I5: - | J5: 0 | K5: 0.42929484
A6: 45901 | B6: 15 | C6: 75741 | D6: 75568 | E6: 32351 | F6: 55.03 | G6: 864216 | H6: - | I6: - | J6: 0 | K6: 0.42712666
A7: 45931 | B7: 16 | C7: 91163 | D7: 90901 | E7: 38855 | F7: 55.71 | G7: 899681 | H7: - | I7: - | J7: 0 | K7: 0.42621458
A8: 45962 | B8: 16 | C8: 90283 | D8: 90045 | E8: 38267 | F8: 57.26 | G8: 934062 | H8: - | I8: - | J8: 0 | K8: 0.4238561
A9: 45992 | B9: 16 | C9: 89204 | D9: 88936 | E9: 36624 | F9: 60.09 | G9: 969263 | H9: - | I9: - | J9: 0 | K9: 0.41056455
A10: 1月 | B10: 17 | C10: 84307 | D10: 84083 | E10: 36133 | F10: 60.12 | G10: 1002164 | H10: - | I10: - | J10: 0 | K10: 0.42858837
A11: 2月 | B11: 18 | C11: 75287 | D11: 75073 | E11: 34350 | F11: 63.03 | G11: 1034127 | H11: - | I11: - | J11: 0 | K11: 0.45625407
A12: 3月 | B12: 18 | C12: 84432 | D12: 84166 | E12: 39383 | F12: 59.82 | G12: 1066514 | H12: - | I12: - | J12: 0 | K12: 0.46644637
A13: 4月 | B13: 18 | C13: 85718 | D13: 85509 | E13: 38348 | F13: 58.16 | G13: 1101270 | H13: 31954 | I13: 1.3562308 | J13: 0 | K13: 0.44737395
A14: 5月 | B14: 19 | C14: 92051 | D14: 91784 | E14: 44432 | F14: 61.82 | G14: 1144514 | H14: 37024 | I14: 1.3354581 | J14: 0 | K14: 0.48268894
A15: 6月 | B15: 19 | C15: - | D15: - | E15: - | F15: 60.54 | G15: 1169036 | H15: 24821 | I15: 1.3606221 | J15: 0 | K15: 数据截止至6/25
A16: 年均值 | B16: 16.5 | C16: 84799.545 | D16: 84566.727 | E16: 37023.455 | F16: 58.825833 | G16: 985559.25 | H16: 31266.333 | I16: 1.3507703 | J16: 0

Sheet 数据洞察
A1: 山池咖啡 · 品牌数据分析洞察
A3: 一、关键数据发现
A4: 指标 | B4: 年均值 | C4: 洞察说明
A5: 月均消费人数 | B5: =品牌原始数据!E16 -> 37023.455 | C5: 月均37,023人，是企微拉新的流量池
A6: 月均客单价 | B6: =品牌原始数据!F16 -> 58.825833 | C6: 每多到店1次=+58.83元增量GMV
A7: 月均订单数 | B7: =品牌原始数据!D16 -> 84566.727 | C7: 月均84,567单，连锁规模稳健
A8: 门店数（最新） | B8: 19 | C8: 从13家→19家，扩张迅速
A9: 会员体量（累计） | B9: =品牌原始数据!G16 -> 985559.25 | C9: 累计98.6万会员，基数大
A10: 会员月均消费人数 | B10: =品牌原始数据!H16 -> 31266.333 | C10: 月均31,266人，仅占会员体量3.2%
A11: 会员消费频次 | B11: =品牌原始数据!I16 -> 1.3507703 | C11: 仅1.35次/月，行业均值2.25次，差距0.9次
A12: 企微现有好友 | B12: =品牌原始数据!J16 -> 0 | C12: 当前为0！私域完全从零起步
A13: 人均拉新成本 | B13: 0.5 | C13: 约0.5元/人（品牌未提供，行业均值假设）
A15: 二、核心结论
A16: 1. 会员消费频次仅1.35次/月，远低于行业均值2.25次/月（益普索2026茶咖报告），提频空间达+0.9次（67%）。
A17: 2. 企微好友当前为0，私域完全从零起步。这意味着所有增量都是"新建"的，ROI的分子会从第2-3个月才开始显现。
A18: 3. 人均拉新成本仅0.42元，获客成本极低。月均消费人数37,023人，假设8%转化率=月拉新约3,000人。
A19: 4. 会员体量98.6万，但月活跃仅3.1万（活跃率3.2%）。大量沉睡会员是未来唤醒的潜在池。
A20: 5. 客单价58.83元稳定，每提升1次到店频次=+58.83元增量收入。
A22: 三、模型调整说明（vs 之前的通用模型）
A23: 调整项 | B23: 通用模型 | C23: 基于实际数据的调整 | D23: 调整原因
A24: 提频幅度 | B24: +0.7次/月 | C24: +0.5次/月 | D24: 当前频次1.35很低，+0.5到1.85已是有意义提升
A25: 沉睡会员唤醒 | B25: 适用 | C25: 暂不适用 | D25: 企微好友=0，无现有好友池可唤醒。积累后可启用
A26: 活跃好友基数 | B26: 企微好友总数 | C26: 月拉新×活跃率×6个月 | D26: 从零起步，用逐月积累中位数计算
A27: 拉新规模 | B27: 需品牌提供 | C27: 消费人数×8%≈3,000人/月 | D27: 基于月均消费人数37,023和行业8%转化率

Sheet ROI测算模型
A1: 山池咖啡 · 私域运营ROI测算（基于实际数据）
A3: 一、品牌基准参数（从品牌数据自动引用）
A4: 指标 | B4: 年均值 | C4: 公式说明
A5: 月均消费人数 | B5: =品牌原始数据!E16 -> 37023.455 | C5: 月均到店消费人数=拉新流量池
A6: 月均客单价（元） | B6: =品牌原始数据!F16 -> 58.825833 | C6: 增量GMV乘数：每多1次到店=+客单价
A7: 月均订单数 | B7: =品牌原始数据!D16 -> 84566.727 | C7: 辅助：门店经营规模
A8: 门店数（最新） | B8: 19 | C8: 辅助：单店效率颗粒度
A9: 会员体量（累计） | B9: =品牌原始数据!G16 -> 985559.25 | C9: 会员存量池：98.6万（活跃率仅3.2%）
A10: 会员月均消费人数 | B10: =品牌原始数据!H16 -> 31266.333 | C10: 会员月活跃3.1万人
A11: 会员消费频次（次/月） | B11: =品牌原始数据!I16 -> 1.3507703 | C11: 当前1.35次，行业均值2.25次
A12: 人均拉新成本（元） | B12: 0.5 | C12: 企微拉新激励成本（利益点），品牌未提供，按行业均值0.5元假设
A14: 二、拉新假设参数（蓝色可调整）
A15: 假设指标 | B15: 默认值 | C15: 设定依据
A16: 企微转化率 | B16: 0.08 | C16: 月均消费人数的8%，约3,000人/月
A17: 月拉新目标（人） | B17: =ROUND(B5*B16,0) -> 2962 | C17: 消费人数 × 企微转化率
A18: 活跃率 | B18: 0.7 | C18: 拉新好友中持续活跃的比例
A19: 平均运营月数 | B19: 6 | C19: 逐月积累的中位数（1-12月中位=6）
A21: 三、运营假设参数（蓝色可调整）
A22: 提频幅度（次/月） | B22: 0.5 | C22: 从1.35→1.85次，保守估计（之前通用模型用0.7，此处下调）
A23: 新品触达转化率 | B23: 0.05 | C23: 精准推送后额外消费的转化
A24: 连带提升率 | B24: 0.08 | C24: 到店后多消费的比例
A25: 连带增额系数 | B25: 0.3 | C25: 连带消费额≈客单价的30%
A26: 毛利率 | B26: 0.6 | C26: 咖啡行业均值
A27: SaaS年费（元） | B27: 0 | C27: iCC SCRM工具年费，待确认
A28: 月运营人力成本（元） | B28: 0 | C28: 品牌侧配合人力，待确认
A30: 四、衍生指标（自动计算）
A31: 衍生指标 | B31: 计算结果 | C31: 公式说明
A32: 年均活跃好友数 | B32: =ROUND(B17*B18*B19,0) -> 12440 | C32: 月拉新×活跃率×平均运营月数（逐月积累）
A33: 年新增企微好友 | B33: =B17*12 -> 35544 | C33: 月拉新×12个月
A34: 会员活跃率 | B34: =IFERROR(B10/B9,0) -> 0.031724458 | C34: 月均消费会员÷会员体量（≈3.2%）
A35: 行业频次差距 | B35: =2.25-B11 -> 0.89922968 | C35: 行业均值2.25 - 当前1.35 = 0.9次
A37: 五、月增量GMV测算
A38: 增量来源 | B38: 月增量GMV | C38: 计算逻辑
A39: ① 到店频次提升 | B39: =ROUND(B32*B22*B6,0) -> 365897 | C39: 年均活跃好友 × 提频幅度 × 客单价
A40: ② 沉睡会员唤醒 | B40: =0 -> 0 | C40: 当前企微好友=0，无现有池可唤醒（积累后可启用）
A41: ③ 新品转化 | B41: =ROUND(B32*B23*B6,0) -> 36590 | C41: 年均活跃好友 × 新品转化率 × 客单价
A42: ④ 连带提升 | B42: =ROUND(B32*B24*B6*B25,0) -> 17563 | C42: 年均活跃好友 × 连带率 × 客单价 × 系数
A43: 月增量GMV合计 | B43: =SUM(B39:B42) -> 420050 | C43: 四项增量之和
A44: 年增量GMV | B44: =B43*12 -> 5040600 | C44: 月增量×12个月
A46: 六、投入成本
A47: 成本项 | B47: 年度金额 | C47: 公式说明
A48: 年拉新成本 | B48: =ROUND(B17*12*B12,0) -> 17772 | C48: 年拉新人数×人均拉新成本
A49: SaaS年费 | B49: =B27 -> 0 | C49: 企微SCRM工具年费
A50: 年运营人力 | B50: =B28*12 -> 0 | C50: 月人力×12
A51: 总投入成本 | B51: =SUM(B48:B50) -> 17772 | C51: 三项成本之和
A53: 七、ROI测算结果
A54: 年增量毛利 | B54: =B44*B26 -> 3024360 | C54: 年增量GMV × 毛利率
A55: 年净收益 | B55: =B54-B51 -> 3006588 | C55: 年增量毛利 - 总投入成本
A56: ROI | B56: =IFERROR(B55/B51,0) -> 169.17556 | C56: 年净收益 ÷ 总投入成本
A58: 八、场景分析（调整拉新目标看不同效果）
A59: 场景 | B59: 月拉新目标 | C59: 年均活跃好友 | D59: 年增量GMV | E59: 总投入 | F59: ROI
A60: 保守 | B60: =ROUND(B5*0.05,0) -> 1851 | C60: =ROUND(B60*$B$18*$B$19,0) -> 7774 | D60: =ROUND(C60*($B$22*$B$6+$B$23*$B$6+$B$24*$B$6*$B$25)*12,0) -> 3149965 | E60: =ROUND(B60*12*$B$12,0)+$B$27+$B$28*12 -> 11106 | F60: =IFERROR((D60*$B$26-E60)/E60,0) -> 169.17639
A61: 基准 | B61: =B17 -> 2962 | C61: =ROUND(B61*$B$18*$B$19,0) -> 12440 | D61: =ROUND(C61*($B$22*$B$6+$B$23*$B$6+$B$24*$B$6*$B$25)*12,0) -> 5040593 | E61: =ROUND(B61*12*$B$12,0)+$B$27+$B$28*12 -> 17772 | F61: =IFERROR((D61*$B$26-E61)/E61,0) -> 169.17532
A62: 乐观 | B62: =ROUND(B5*0.12,0) -> 4443 | C62: =ROUND(B62*$B$18*$B$19,0) -> 18661 | D62: =ROUND(C62*($B$22*$B$6+$B$23*$B$6+$B$24*$B$6*$B$25)*12,0) -> 7561294 | E62: =ROUND(B62*12*$B$12,0)+$B$27+$B$28*12 -> 26658 | F62: =IFERROR((D62*$B$26-E62)/E62,0) -> 169.18442
A64: 九、逐月积累模拟（基准场景）
A65: 月份 | B65: 当月拉新 | C65: 累计拉新 | D65: 当月活跃好友 | E65: 当月增量GMV | F65: 累计增量GMV
A66: 第1月 | B66: =$B$17 -> 2962 | C66: =B66 -> 2962 | D66: =ROUND(C66*$B$18,0) -> 2073 | E66: =ROUND(D66*($B$22+$B$23+$B$24*$B$25)*$B$6,0) -> 69997 | F66: =E66 -> 69997
A67: 第2月 | B67: =$B$17 -> 2962 | C67: =C66+B67 -> 5924 | D67: =ROUND(C67*$B$18,0) -> 4147 | E67: =ROUND(D67*($B$22+$B$23+$B$24*$B$25)*$B$6,0) -> 140028 | F67: =F66+E67 -> 210025
A68: 第3月 | B68: =$B$17 -> 2962 | C68: =C67+B68 -> 8886 | D68: =ROUND(C68*$B$18,0) -> 6220 | E68: =ROUND(D68*($B$22+$B$23+$B$24*$B$25)*$B$6,0) -> 210025 | F68: =F67+E68 -> 420050
A69: 第4月 | B69: =$B$17 -> 2962 | C69: =C68+B69 -> 11848 | D69: =ROUND(C69*$B$18,0) -> 8294 | E69: =ROUND(D69*($B$22+$B$23+$B$24*$B$25)*$B$6,0) -> 280055 | F69: =F68+E69 -> 700105
A70: 第5月 | B70: =$B$17 -> 2962 | C70: =C69+B70 -> 14810 | D70: =ROUND(C70*$B$18,0) -> 10367 | E70: =ROUND(D70*($B$22+$B$23+$B$24*$B$25)*$B$6,0) -> 350052 | F70: =F69+E70 -> 1050157
A71: 第6月 | B71: =$B$17 -> 2962 | C71: =C70+B71 -> 17772 | D71: =ROUND(C71*$B$18,0) -> 12440 | E71: =ROUND(D71*($B$22+$B$23+$B$24*$B$25)*$B$6,0) -> 420049 | F71: =F70+E71 -> 1470206
A72: 第7月 | B72: =$B$17 -> 2962 | C72: =C71+B72 -> 20734 | D72: =ROUND(C72*$B$18,0) -> 14514 | E72: =ROUND(D72*($B$22+$B$23+$B$24*$B$25)*$B$6,0) -> 490080 | F72: =F71+E72 -> 1960286
A73: 第8月 | B73: =$B$17 -> 2962 | C73: =C72+B73 -> 23696 | D73: =ROUND(C73*$B$18,0) -> 16587 | E73: =ROUND(D73*($B$22+$B$23+$B$24*$B$25)*$B$6,0) -> 560077 | F73: =F72+E73 -> 2520363
A74: 第9月 | B74: =$B$17 -> 2962 | C74: =C73+B74 -> 26658 | D74: =ROUND(C74*$B$18,0) -> 18661 | E74: =ROUND(D74*($B$22+$B$23+$B$24*$B$25)*$B$6,0) -> 630108 | F74: =F73+E74 -> 3150471
A75: 第10月 | B75: =$B$17 -> 2962 | C75: =C74+B75 -> 29620 | D75: =ROUND(C75*$B$18,0) -> 20734 | E75: =ROUND(D75*($B$22+$B$23+$B$24*$B$25)*$B$6,0) -> 700105 | F75: =F74+E75 -> 3850576
A76: 第11月 | B76: =$B$17 -> 2962 | C76: =C75+B76 -> 32582 | D76: =ROUND(C76*$B$18,0) -> 22807 | E76: =ROUND(D76*($B$22+$B$23+$B$24*$B$25)*$B$6,0) -> 770102 | F76: =F75+E76 -> 4620678
A77: 第12月 | B77: =$B$17 -> 2962 | C77: =C76+B77 -> 35544 | D77: =ROUND(C77*$B$18,0) -> 24881 | E77: =ROUND(D77*($B$22+$B$23+$B$24*$B$25)*$B$6,0) -> 840133 | F77: =F76+E77 -> 5460811
A78: 年度合计 | B78: =C77 -> 35544 | E78: =F77 -> 5460811
A80: 说明：绿色=跨Sheet引用品牌数据 | 蓝色=可调假设参数 | 黑色=公式计算 | 黄底=可输入调整
